{"skeleton":{"width":214.36,"height":212,"spine":"3.6.0","hash":" ","name":"armatureName"},"bones":[{"name":"root"},{"name":"14","parent":"root"},{"x":-60.0688,"y":31.1655,"scaleX":0.7,"scaleY":0.75,"name":"14_bai1","parent":"14"},{"x":-28.7488,"y":38.9955,"scaleX":0.7,"scaleY":0.75,"name":"14_bai2","parent":"14"},{"x":12.1412,"y":33.7755,"scaleX":0.7,"scaleY":0.75,"name":"14_bai3","parent":"14"},{"x":47.8112,"y":22.4655,"scaleX":0.7,"scaleY":0.75,"name":"14_bai4","parent":"14"},{"x":0.7448,"y":-67.1763,"name":"14_coin","parent":"14"},{"x":53.0907,"y":-44.8836,"scaleX":1,"scaleY":1,"name":"14_lock","parent":"14"},{"x":-49.4007,"y":-44.106,"scaleX":1,"scaleY":1,"name":"14_sam","parent":"14"}],"slots":[{"name":"14_BG","bone":"14","attachment":"14_BG"},{"name":"14_coin","bone":"14_coin","attachment":"14_coin"},{"name":"14_bai1","bone":"14_bai1","attachment":"14_bai1"},{"name":"14_bai2","bone":"14_bai2","attachment":"14_bai2"},{"name":"14_bai3","bone":"14_bai3","attachment":"14_bai3"},{"name":"14_bai4","bone":"14_bai4","attachment":"14_bai4"},{"name":"14_lock","bone":"14_lock","attachment":"14_lock"},{"name":"14_sam","bone":"14_sam","attachment":"14_sam"}],"skins":{"default":{"14_bai3":{"14_bai3":{"name":"14_bai3","width":100,"height":121,"x":7.52,"y":-4.72}},"14_bai4":{"14_bai4":{"name":"14_bai4","width":113,"height":127,"x":3.35,"y":-4.41}},"14_lock":{"14_lock":{"name":"14_lock","width":99,"height":54,"x":1.48,"y":3.47}},"14_sam":{"14_sam":{"name":"14_sam","width":110,"height":50,"x":-0.67,"y":4.08}},"14_BG":{"14_BG":{"name":"14_BG","width":206,"height":185,"y":-0.5,"path":"WSAMLOC"}},"14_coin":{"14_coin":{"name":"14_coin","width":153,"height":105,"x":-2.58,"y":39.63}},"14_bai1":{"14_bai1":{"name":"14_bai1","width":107,"height":124,"x":11.23,"y":2.39}},"14_bai2":{"14_bai2":{"name":"14_bai2","width":83,"height":111,"x":13.91,"y":-2.94}}}},"animations":{"animation":{"bones":{"14_bai1":{"translate":[{"time":0,"curve":[0.39225,0,0.84775,0.9925],"x":-6.29,"y":23.06},{"time":0.4667,"x":-6.29,"y":23.06},{"time":0.6334,"curve":[0.25,0,0.75,1]},{"time":1.1334,"curve":[0.25,0,0.75,1],"y":6.26},{"time":1.6001,"curve":[0.0625,0,0.9375,1],"y":2.68},{"time":2.1334,"curve":[0.25,0,0.75,1],"y":6.26},{"time":2.6667,"y":-4.7}],"rotate":[{"time":0,"curve":[0.39225,0,0.84775,0.9925],"angle":120},{"time":0.1333,"angle":0},{"time":0.3,"angle":-120},{"time":0.4667,"angle":120},{"time":0.6334,"angle":0}],"scale":[{"time":0,"curve":[0.39225,0,0.84775,0.9925],"x":0,"y":0},{"time":0.4667,"x":0,"y":0},{"time":0.6334,"x":1,"y":1}],"shear":[{"time":0,"curve":[0.39225,0,0.84775,0.9925]},{"time":0.1333},{"time":0.3},{"time":0.4667},{"time":0.6334}]},"14_bai2":{"translate":[{"time":0,"curve":"stepped","x":-39.3,"y":20.44},{"time":0.5667,"x":-39.3,"y":20.44},{"time":0.7334,"curve":[0.25,0,0.75,1]},{"time":1.2001,"curve":[0.25,0,0.75,1],"y":6.26},{"time":1.6668,"curve":[0.0625,0,0.9375,1],"y":2.09},{"time":2.1668,"curve":[0.25,0,0.75,1],"y":6.26},{"time":2.6335,"y":-4.7}],"rotate":[{"time":0,"curve":"stepped","angle":120},{"time":0.1,"curve":[0.39225,0,0.84775,0.9925],"angle":120},{"time":0.2333,"angle":0},{"time":0.4,"angle":-120},{"time":0.5667,"angle":120},{"time":0.7334,"angle":0}],"scale":[{"time":0,"curve":"stepped","x":0,"y":0},{"time":0.5667,"x":0,"y":0},{"time":0.7334,"x":1,"y":1}],"shear":[{"time":0,"curve":"stepped"},{"time":0.1,"curve":[0.39225,0,0.84775,0.9925]},{"time":0.2333},{"time":0.4},{"time":0.5667},{"time":0.7334}]},"14_bai3":{"translate":[{"time":0,"curve":"stepped","x":-79.65,"y":27.25},{"time":0.6667,"x":-79.65,"y":27.25},{"time":0.8334,"curve":[0.25,0,0.75,1]},{"time":1.3001,"curve":[0.25,0,0.75,1],"y":6.26},{"time":1.7001,"curve":[0.0625,0,0.9375,1],"y":1.25},{"time":2.2001,"curve":[0.25,0,0.75,1],"y":6.26},{"time":2.6668,"y":-4.7}],"rotate":[{"time":0,"curve":"stepped","angle":120},{"time":0.2,"curve":[0.39225,0,0.84775,0.9925],"angle":120},{"time":0.3333,"angle":0},{"time":0.5,"angle":-120},{"time":0.6667,"angle":120},{"time":0.8334,"angle":0}],"scale":[{"time":0,"curve":"stepped","x":0,"y":0},{"time":0.6667,"x":0,"y":0},{"time":0.8334,"x":1,"y":1}],"shear":[{"time":0,"curve":"stepped"},{"time":0.2,"curve":[0.39225,0,0.84775,0.9925]},{"time":0.3333},{"time":0.5},{"time":0.6667},{"time":0.8334}]},"14_bai4":{"translate":[{"time":0,"curve":"stepped","x":-113.18,"y":38.25},{"time":0.7667,"x":-113.18,"y":38.25},{"time":0.9334,"curve":[0.25,0,0.75,1]},{"time":1.3667,"curve":[0.25,0,0.75,1],"y":6.26},{"time":1.7667,"curve":[0.0625,0,0.9375,1]},{"time":2.2334,"curve":[0.25,0,0.75,1],"y":6.26},{"time":2.6667,"y":-4.7}],"rotate":[{"time":0,"curve":"stepped","angle":120},{"time":0.3,"curve":[0.39225,0,0.84775,0.9925],"angle":120},{"time":0.4333,"angle":0},{"time":0.6,"angle":-120},{"time":0.7667,"angle":120},{"time":0.9334,"angle":0}],"scale":[{"time":0,"curve":"stepped","x":0,"y":0},{"time":0.7667,"x":0,"y":0},{"time":0.9334,"x":1,"y":1}],"shear":[{"time":0,"curve":"stepped"},{"time":0.3,"curve":[0.39225,0,0.84775,0.9925]},{"time":0.4333},{"time":0.6},{"time":0.7667},{"time":0.9334}]},"14_sam":{"translate":[{"time":0,"curve":[0.645,0,0.821,0.77],"x":-81.36},{"time":0.2667,"curve":[0.25,0,0.75,1],"x":8.48},{"time":0.3,"curve":[0.25,0,0.75,1],"x":8.48},{"time":0.4333,"curve":[0.25,0,0.75,1],"x":-5.65},{"time":0.4666,"curve":[0.25,0,0.75,1],"x":-5.65},{"time":0.5666}],"scale":[{"time":0,"curve":[0.645,0,0.821,0.77],"x":1,"y":1},{"time":0.2667,"curve":[0.25,0,0.75,1],"x":1,"y":1},{"time":0.3,"curve":[0.25,0,0.75,1],"x":0.86,"y":1},{"time":0.4333,"curve":[0.25,0,0.75,1],"x":0.86,"y":1},{"time":0.4666,"curve":[0.25,0,0.75,1],"x":1.02,"y":1},{"time":0.5666,"x":1.02,"y":1},{"time":0.5999,"x":1,"y":1}]},"14_lock":{"translate":[{"time":0,"curve":[0.645,0,0.821,0.77],"x":71.75},{"time":0.2667,"curve":[0.25,0,0.75,1],"x":-11.87},{"time":0.3,"curve":[0.25,0,0.75,1],"x":-11.87},{"time":0.4333,"curve":[0.25,0,0.75,1],"x":4.52},{"time":0.4666,"curve":[0.25,0,0.75,1],"x":4.52},{"time":0.5666}],"scale":[{"time":0,"curve":[0.645,0,0.821,0.77],"x":1,"y":1},{"time":0.2667,"curve":[0.25,0,0.75,1],"x":1,"y":1},{"time":0.3,"curve":[0.25,0,0.75,1],"x":0.86,"y":1},{"time":0.4333,"curve":[0.25,0,0.75,1],"x":0.86,"y":1},{"time":0.4666,"curve":[0.25,0,0.75,1],"x":1.02,"y":1},{"time":0.5666,"x":1.02,"y":1},{"time":0.5999,"x":1,"y":1}]},"14_coin":{"scale":[{"time":0,"curve":[0.25,0,0.75,1],"x":1,"y":1},{"time":0.6667,"curve":[0.25,0,0.75,1],"x":1.06,"y":1.06},{"time":1.3334,"curve":[0.25,0,0.75,1],"x":1,"y":1},{"time":2.0001,"curve":[0.25,0,0.75,1],"x":1.06,"y":1.06},{"time":2.6668,"x":1,"y":1}]}}}}}